sqlacodegen/__init__.py
sqlacodegen/codegen.py
sqlacodegen/main.py
sqlacodegen/dialects/__init__.py
sqlacodegen/dialects/postgresql.py
flask_sqlacodegen-2.0.0.dist-info/LICENSE
flask_sqlacodegen-2.0.0.dist-info/METADATA
flask_sqlacodegen-2.0.0.dist-info/WHEEL
flask_sqlacodegen-2.0.0.dist-info/entry_points.txt
flask_sqlacodegen-2.0.0.dist-info/top_level.txt
flask_sqlacodegen-2.0.0.dist-info/RECORD
